LICENSE
MANIFEST.in
README.md
setup.py
aloha/__init__.py
aloha/decorators.py
aloha/fields.py
aloha/widgets.py
aloha/static/aloha/build.txt
aloha/static/aloha/package.json
aloha/static/aloha/css/aloha-common-extra.css
aloha/static/aloha/css/aloha-core.css
aloha/static/aloha/css/aloha-reset.css
aloha/static/aloha/css/aloha-sidebar.css
aloha/static/aloha/css/aloha.css
aloha/static/aloha/demo/block/dragdrop.html
aloha/static/aloha/demo/block/index.css
aloha/static/aloha/demo/block/index.html
aloha/static/aloha/demo/block/blockdemo/css/block.css
aloha/static/aloha/demo/block/blockdemo/img/stock-quote-aapl.gif
aloha/static/aloha/demo/block/blockdemo/img/stock-quote-msft.gif
aloha/static/aloha/demo/block/blockdemo/lib/block.js
aloha/static/aloha/demo/block/blockdemo/lib/blockdemo-plugin.js
aloha/static/aloha/demo/block/blockdemo/res/vcard.html
aloha/static/aloha/demo/block/blockdemo/vendor/underscore.js
aloha/static/aloha/demo/boilerplate/apple-touch-icon-114x114-precomposed.png
aloha/static/aloha/demo/boilerplate/apple-touch-icon-57x57-precomposed.png
aloha/static/aloha/demo/boilerplate/apple-touch-icon-72x72-precomposed.png
aloha/static/aloha/demo/boilerplate/apple-touch-icon-precomposed.png
aloha/static/aloha/demo/boilerplate/apple-touch-icon.png
aloha/static/aloha/demo/boilerplate/captioned-image.html
aloha/static/aloha/demo/boilerplate/crossdomain.xml
aloha/static/aloha/demo/boilerplate/fake-jquery.js
aloha/static/aloha/demo/boilerplate/favicon.ico
aloha/static/aloha/demo/boilerplate/humans.txt
aloha/static/aloha/demo/boilerplate/index.html
aloha/static/aloha/demo/boilerplate/ribbon-example.js
aloha/static/aloha/demo/boilerplate/robots.txt
aloha/static/aloha/demo/boilerplate/css/style.css
aloha/static/aloha/demo/boilerplate/img/aloha-editor-logo.png
aloha/static/aloha/demo/boilerplate/img/loading.gif
aloha/static/aloha/demo/boilerplate/img/loading1.gif
aloha/static/aloha/demo/boilerplate/img/navigation-bg-hover.png
django_aloha_edit.egg-info/PKG-INFO
django_aloha_edit.egg-info/SOURCES.txt
django_aloha_edit.egg-info/dependency_links.txt
django_aloha_edit.egg-info/requires.txt
django_aloha_edit.egg-info/top_level.txt