Metadata-Version: 1.1
Name: django-aloha-edit
Version: 0.3.2
Summary: Django Aloha Edit
Home-page: https://github.com/ntucker/django-aloha-edit
Author: Nathaniel Tucker
Author-email: me@ntucker.me
License: BSD
Platform: UNKNOWN
Classifier: Development Status :: 4 - Beta
Classifier: Environment :: Web Environment
Classifier: Framework :: Django
Classifier: Intended Audience :: Developers
Classifier: License :: OSI Approved :: BSD License
Classifier: Operating System :: OS Independent
Classifier: Programming Language :: Python
Classifier: Programming Language :: Python :: 2
Classifier: Programming Language :: Python :: 2.7
Classifier: Programming Language :: Python :: 3
Classifier: Programming Language :: Python :: 3.3
